{
  "generated_at": "2026-05-27T23:59:53.806Z",
  "as_of_date": "2026-05-27",
  "symbol": "032830.KS",
  "stock_data": {
    "symbol": "032830.KS",
    "company_name": "삼성생명",
    "english_name": "Samsung Life Insurance",
    "current_price": 92440,
    "price_change_1d": 1.94,
    "currency": "KRW",
    "gics_sector": "보험",
    "gics_industry": "생명보험",
    "ibd_industry_group": "금융",
    "ibd_group_rank": 4,
    "stage": 2,
    "rating": "Strong Buy",
    "composite_score": 82
  },
  "fundamentals": {
    "eps_rating": 75,
    "rs_rating": 80,
    "sales_growth_qq": 3,
    "sales_growth_yy": 6,
    "eps_growth_qq": 7,
    "eps_growth_yy": 12,
    "adr_percent": 3.51,
    "market_cap_usd": 11428571428.571428
  },
  "bars": [
    {
      "date": "2025-12-11",
      "open": 75752,
      "high": 75779,
      "low": 75542,
      "close": 75582,
      "volume": 990659,
      "ma_50": 75582,
      "ma_150": 75582,
      "ma_200": 75582
    },
    {
      "date": "2025-12-14",
      "open": 75598,
      "high": 76668,
      "low": 75008,
      "close": 76199,
      "volume": 874076,
      "ma_50": 75606,
      "ma_150": 75590,
      "ma_200": 75588
    },
    {
      "date": "2025-12-15",
      "open": 76022,
      "high": 76415,
      "low": 75264,
      "close": 75796,
      "volume": 847489,
      "ma_50": 75614,
      "ma_150": 75593,
      "ma_200": 75590
    },
    {
      "date": "2025-12-16",
      "open": 75875,
      "high": 76273,
      "low": 75145,
      "close": 75751,
      "volume": 105513,
      "ma_50": 75619,
      "ma_150": 75595,
      "ma_200": 75592
    },
    {
      "date": "2025-12-17",
      "open": 75585,
      "high": 75714,
      "low": 75561,
      "close": 75589,
      "volume": 798526,
      "ma_50": 75618,
      "ma_150": 75595,
      "ma_200": 75592
    },
    {
      "date": "2025-12-18",
      "open": 75407,
      "high": 76454,
      "low": 75401,
      "close": 76077,
      "volume": 236291,
      "ma_50": 75636,
      "ma_150": 75601,
      "ma_200": 75597
    },
    {
      "date": "2025-12-21",
      "open": 76250,
      "high": 76707,
      "low": 75346,
      "close": 75375,
      "volume": 183343,
      "ma_50": 75626,
      "ma_150": 75598,
      "ma_200": 75595
    },
    {
      "date": "2025-12-22",
      "open": 75211,
      "high": 76322,
      "low": 74847,
      "close": 76030,
      "volume": 360286,
      "ma_50": 75642,
      "ma_150": 75604,
      "ma_200": 75599
    },
    {
      "date": "2025-12-23",
      "open": 75955,
      "high": 77846,
      "low": 75484,
      "close": 77386,
      "volume": 131449,
      "ma_50": 75710,
      "ma_150": 75628,
      "ma_200": 75617
    },
    {
      "date": "2025-12-24",
      "open": 77287,
      "high": 77785,
      "low": 76789,
      "close": 77732,
      "volume": 872102,
      "ma_50": 75789,
      "ma_150": 75656,
      "ma_200": 75638
    },
    {
      "date": "2025-12-25",
      "open": 77852,
      "high": 78252,
      "low": 77538,
      "close": 78005,
      "volume": 636559,
      "ma_50": 75876,
      "ma_150": 75687,
      "ma_200": 75661
    },
    {
      "date": "2025-12-28",
      "open": 77913,
      "high": 79457,
      "low": 77748,
      "close": 79206,
      "volume": 485455,
      "ma_50": 76007,
      "ma_150": 75733,
      "ma_200": 75697
    },
    {
      "date": "2025-12-29",
      "open": 79038,
      "high": 79149,
      "low": 77582,
      "close": 77947,
      "volume": 855742,
      "ma_50": 76083,
      "ma_150": 75763,
      "ma_200": 75719
    },
    {
      "date": "2025-12-30",
      "open": 78017,
      "high": 78230,
      "low": 77947,
      "close": 78050,
      "volume": 455697,
      "ma_50": 76160,
      "ma_150": 75793,
      "ma_200": 75742
    },
    {
      "date": "2025-12-31",
      "open": 77995,
      "high": 78559,
      "low": 76548,
      "close": 76903,
      "volume": 570095,
      "ma_50": 76189,
      "ma_150": 75808,
      "ma_200": 75754
    },
    {
      "date": "2026-01-01",
      "open": 76819,
      "high": 78567,
      "low": 76241,
      "close": 78430,
      "volume": 733583,
      "ma_50": 76277,
      "ma_150": 75842,
      "ma_200": 75780
    },
    {
      "date": "2026-01-04",
      "open": 78286,
      "high": 79745,
      "low": 77687,
      "close": 79628,
      "volume": 872978,
      "ma_50": 76408,
      "ma_150": 75893,
      "ma_200": 75819
    },
    {
      "date": "2026-01-05",
      "open": 79760,
      "high": 80401,
      "low": 79413,
      "close": 80087,
      "volume": 645389,
      "ma_50": 76553,
      "ma_150": 75948,
      "ma_200": 75861
    },
    {
      "date": "2026-01-06",
      "open": 80106,
      "high": 81577,
      "low": 79811,
      "close": 81289,
      "volume": 774008,
      "ma_50": 76738,
      "ma_150": 76019,
      "ma_200": 75915
    },
    {
      "date": "2026-01-07",
      "open": 81284,
      "high": 81596,
      "low": 80049,
      "close": 80149,
      "volume": 479930,
      "ma_50": 76872,
      "ma_150": 76074,
      "ma_200": 75957
    },
    {
      "date": "2026-01-08",
      "open": 80303,
      "high": 80904,
      "low": 78873,
      "close": 79282,
      "volume": 450818,
      "ma_50": 76967,
      "ma_150": 76116,
      "ma_200": 75990
    },
    {
      "date": "2026-01-11",
      "open": 79356,
      "high": 79861,
      "low": 79219,
      "close": 79536,
      "volume": 735918,
      "ma_50": 77067,
      "ma_150": 76161,
      "ma_200": 76026
    },
    {
      "date": "2026-01-12",
      "open": 79648,
      "high": 80346,
      "low": 79371,
      "close": 80196,
      "volume": 155075,
      "ma_50": 77190,
      "ma_150": 76215,
      "ma_200": 76067
    },
    {
      "date": "2026-01-13",
      "open": 80360,
      "high": 81051,
      "low": 80177,
      "close": 80439,
      "volume": 765277,
      "ma_50": 77318,
      "ma_150": 76271,
      "ma_200": 76111
    },
    {
      "date": "2026-01-14",
      "open": 80362,
      "high": 81558,
      "low": 79721,
      "close": 81181,
      "volume": 678064,
      "ma_50": 77469,
      "ma_150": 76336,
      "ma_200": 76161
    },
    {
      "date": "2026-01-15",
      "open": 81088,
      "high": 82910,
      "low": 80826,
      "close": 82389,
      "volume": 430293,
      "ma_50": 77662,
      "ma_150": 76416,
      "ma_200": 76223
    },
    {
      "date": "2026-01-18",
      "open": 82537,
      "high": 83014,
      "low": 82469,
      "close": 82754,
      "volume": 410667,
      "ma_50": 77862,
      "ma_150": 76500,
      "ma_200": 76288
    },
    {
      "date": "2026-01-19",
      "open": 82687,
      "high": 83202,
      "low": 81207,
      "close": 81646,
      "volume": 332111,
      "ma_50": 78010,
      "ma_150": 76568,
      "ma_200": 76341
    },
    {
      "date": "2026-01-20",
      "open": 81619,
      "high": 82029,
      "low": 80314,
      "close": 80689,
      "volume": 539930,
      "ma_50": 78115,
      "ma_150": 76623,
      "ma_200": 76385
    },
    {
      "date": "2026-01-21",
      "open": 80631,
      "high": 81932,
      "low": 80356,
      "close": 81486,
      "volume": 233852,
      "ma_50": 78247,
      "ma_150": 76687,
      "ma_200": 76435
    },
    {
      "date": "2026-01-22",
      "open": 81298,
      "high": 81892,
      "low": 80701,
      "close": 81728,
      "volume": 745725,
      "ma_50": 78384,
      "ma_150": 76754,
      "ma_200": 76488
    },
    {
      "date": "2026-01-25",
      "open": 81926,
      "high": 82795,
      "low": 81741,
      "close": 82392,
      "volume": 987889,
      "ma_50": 78541,
      "ma_150": 76829,
      "ma_200": 76547
    },
    {
      "date": "2026-01-26",
      "open": 82401,
      "high": 83824,
      "low": 82240,
      "close": 83559,
      "volume": 296150,
      "ma_50": 78738,
      "ma_150": 76918,
      "ma_200": 76617
    },
    {
      "date": "2026-01-27",
      "open": 83523,
      "high": 84274,
      "low": 82897,
      "close": 84246,
      "volume": 355040,
      "ma_50": 78954,
      "ma_150": 77015,
      "ma_200": 76692
    },
    {
      "date": "2026-01-28",
      "open": 84132,
      "high": 84363,
      "low": 83169,
      "close": 83195,
      "volume": 603869,
      "ma_50": 79120,
      "ma_150": 77097,
      "ma_200": 76757
    },
    {
      "date": "2026-01-29",
      "open": 83232,
      "high": 84861,
      "low": 83164,
      "close": 84413,
      "volume": 733173,
      "ma_50": 79328,
      "ma_150": 77193,
      "ma_200": 76833
    },
    {
      "date": "2026-02-01",
      "open": 84526,
      "high": 85140,
      "low": 83294,
      "close": 83442,
      "volume": 464329,
      "ma_50": 79489,
      "ma_150": 77276,
      "ma_200": 76899
    },
    {
      "date": "2026-02-02",
      "open": 83562,
      "high": 83849,
      "low": 82418,
      "close": 82762,
      "volume": 312388,
      "ma_50": 79617,
      "ma_150": 77349,
      "ma_200": 76957
    },
    {
      "date": "2026-02-03",
      "open": 82607,
      "high": 84988,
      "low": 82561,
      "close": 84404,
      "volume": 684276,
      "ma_50": 79805,
      "ma_150": 77442,
      "ma_200": 77031
    },
    {
      "date": "2026-02-04",
      "open": 84562,
      "high": 84656,
      "low": 83340,
      "close": 83870,
      "volume": 613485,
      "ma_50": 79964,
      "ma_150": 77527,
      "ma_200": 77100
    },
    {
      "date": "2026-02-05",
      "open": 83953,
      "high": 85595,
      "low": 83941,
      "close": 85159,
      "volume": 724745,
      "ma_50": 80168,
      "ma_150": 77629,
      "ma_200": 77180
    },
    {
      "date": "2026-02-08",
      "open": 85087,
      "high": 85309,
      "low": 83895,
      "close": 84286,
      "volume": 764161,
      "ma_50": 80330,
      "ma_150": 77717,
      "ma_200": 77250
    },
    {
      "date": "2026-02-09",
      "open": 84360,
      "high": 84725,
      "low": 82683,
      "close": 83188,
      "volume": 674349,
      "ma_50": 80442,
      "ma_150": 77789,
      "ma_200": 77310
    },
    {
      "date": "2026-02-10",
      "open": 83133,
      "high": 84330,
      "low": 82758,
      "close": 84119,
      "volume": 121925,
      "ma_50": 80586,
      "ma_150": 77873,
      "ma_200": 77377
    },
    {
      "date": "2026-02-11",
      "open": 84109,
      "high": 86173,
      "low": 83884,
      "close": 85555,
      "volume": 195893,
      "ma_50": 80781,
      "ma_150": 77975,
      "ma_200": 77459
    },
    {
      "date": "2026-02-12",
      "open": 85576,
      "high": 87655,
      "low": 85151,
      "close": 87076,
      "volume": 631784,
      "ma_50": 81028,
      "ma_150": 78095,
      "ma_200": 77554
    },
    {
      "date": "2026-02-15",
      "open": 86944,
      "high": 87251,
      "low": 86500,
      "close": 87173,
      "volume": 507982,
      "ma_50": 81269,
      "ma_150": 78216,
      "ma_200": 77650
    },
    {
      "date": "2026-02-16",
      "open": 86958,
      "high": 88106,
      "low": 86302,
      "close": 87784,
      "volume": 961381,
      "ma_50": 81524,
      "ma_150": 78342,
      "ma_200": 77751
    },
    {
      "date": "2026-02-17",
      "open": 87762,
      "high": 89750,
      "low": 87355,
      "close": 89149,
      "volume": 717198,
      "ma_50": 81823,
      "ma_150": 78485,
      "ma_200": 77864
    },
    {
      "date": "2026-02-18",
      "open": 89012,
      "high": 90223,
      "low": 88371,
      "close": 90017,
      "volume": 905268,
      "ma_50": 82145,
      "ma_150": 78638,
      "ma_200": 77985
    },
    {
      "date": "2026-02-19",
      "open": 90237,
      "high": 90724,
      "low": 90140,
      "close": 90181,
      "volume": 948541,
      "ma_50": 82460,
      "ma_150": 78791,
      "ma_200": 78107
    },
    {
      "date": "2026-02-22",
      "open": 90116,
      "high": 90705,
      "low": 90006,
      "close": 90424,
      "volume": 796426,
      "ma_50": 82772,
      "ma_150": 78945,
      "ma_200": 78229
    },
    {
      "date": "2026-02-23",
      "open": 90479,
      "high": 92398,
      "low": 90190,
      "close": 91720,
      "volume": 294772,
      "ma_50": 83123,
      "ma_150": 79114,
      "ma_200": 78363
    },
    {
      "date": "2026-02-24",
      "open": 91709,
      "high": 93056,
      "low": 91245,
      "close": 92565,
      "volume": 308284,
      "ma_50": 83493,
      "ma_150": 79293,
      "ma_200": 78505
    },
    {
      "date": "2026-02-25",
      "open": 92419,
      "high": 94302,
      "low": 92307,
      "close": 93996,
      "volume": 677288,
      "ma_50": 83905,
      "ma_150": 79487,
      "ma_200": 78659
    },
    {
      "date": "2026-02-26",
      "open": 94097,
      "high": 94366,
      "low": 93639,
      "close": 93856,
      "volume": 604357,
      "ma_50": 84295,
      "ma_150": 79678,
      "ma_200": 78810
    },
    {
      "date": "2026-03-01",
      "open": 94023,
      "high": 94392,
      "low": 93487,
      "close": 93487,
      "volume": 797506,
      "ma_50": 84656,
      "ma_150": 79860,
      "ma_200": 78956
    },
    {
      "date": "2026-03-02",
      "open": 93485,
      "high": 93770,
      "low": 93040,
      "close": 93726,
      "volume": 134090,
      "ma_50": 85011,
      "ma_150": 80044,
      "ma_200": 79103
    },
    {
      "date": "2026-03-03",
      "open": 93674,
      "high": 94154,
      "low": 92559,
      "close": 93116,
      "volume": 616210,
      "ma_50": 85329,
      "ma_150": 80217,
      "ma_200": 79242
    },
    {
      "date": "2026-03-04",
      "open": 92899,
      "high": 93610,
      "low": 92318,
      "close": 93457,
      "volume": 999280,
      "ma_50": 85648,
      "ma_150": 80393,
      "ma_200": 79384
    },
    {
      "date": "2026-03-05",
      "open": 93253,
      "high": 94243,
      "low": 93168,
      "close": 93761,
      "volume": 120685,
      "ma_50": 85966,
      "ma_150": 80570,
      "ma_200": 79527
    },
    {
      "date": "2026-03-08",
      "open": 93710,
      "high": 94356,
      "low": 92052,
      "close": 92535,
      "volume": 939065,
      "ma_50": 86224,
      "ma_150": 80728,
      "ma_200": 79656
    },
    {
      "date": "2026-03-09",
      "open": 92531,
      "high": 93222,
      "low": 91411,
      "close": 91773,
      "volume": 729013,
      "ma_50": 86441,
      "ma_150": 80874,
      "ma_200": 79777
    },
    {
      "date": "2026-03-10",
      "open": 91563,
      "high": 93690,
      "low": 91562,
      "close": 93327,
      "volume": 812756,
      "ma_50": 86711,
      "ma_150": 81039,
      "ma_200": 79912
    },
    {
      "date": "2026-03-11",
      "open": 93119,
      "high": 93426,
      "low": 93038,
      "close": 93391,
      "volume": 280800,
      "ma_50": 86973,
      "ma_150": 81203,
      "ma_200": 80046
    },
    {
      "date": "2026-03-12",
      "open": 93404,
      "high": 93741,
      "low": 91811,
      "close": 91960,
      "volume": 632837,
      "ma_50": 87169,
      "ma_150": 81345,
      "ma_200": 80164
    },
    {
      "date": "2026-03-15",
      "open": 91899,
      "high": 92087,
      "low": 91272,
      "close": 91663,
      "volume": 866246,
      "ma_50": 87345,
      "ma_150": 81482,
      "ma_200": 80279
    },
    {
      "date": "2026-03-16",
      "open": 91505,
      "high": 92054,
      "low": 90372,
      "close": 90857,
      "volume": 520689,
      "ma_50": 87483,
      "ma_150": 81606,
      "ma_200": 80384
    },
    {
      "date": "2026-03-17",
      "open": 90879,
      "high": 90965,
      "low": 89156,
      "close": 89408,
      "volume": 133649,
      "ma_50": 87558,
      "ma_150": 81710,
      "ma_200": 80474
    },
    {
      "date": "2026-03-18",
      "open": 89434,
      "high": 90075,
      "low": 88110,
      "close": 88254,
      "volume": 171283,
      "ma_50": 87586,
      "ma_150": 81796,
      "ma_200": 80551
    },
    {
      "date": "2026-03-19",
      "open": 88453,
      "high": 88917,
      "low": 86354,
      "close": 86902,
      "volume": 100914,
      "ma_50": 87559,
      "ma_150": 81864,
      "ma_200": 80615
    },
    {
      "date": "2026-03-22",
      "open": 86731,
      "high": 86829,
      "low": 85343,
      "close": 85602,
      "volume": 806667,
      "ma_50": 87482,
      "ma_150": 81913,
      "ma_200": 80664
    },
    {
      "date": "2026-03-23",
      "open": 85542,
      "high": 87691,
      "low": 85258,
      "close": 87107,
      "volume": 704057,
      "ma_50": 87467,
      "ma_150": 81982,
      "ma_200": 80728
    },
    {
      "date": "2026-03-24",
      "open": 87323,
      "high": 87337,
      "low": 86165,
      "close": 86345,
      "volume": 148683,
      "ma_50": 87423,
      "ma_150": 82040,
      "ma_200": 80784
    },
    {
      "date": "2026-03-25",
      "open": 86199,
      "high": 87139,
      "low": 85741,
      "close": 87129,
      "volume": 901809,
      "ma_50": 87412,
      "ma_150": 82107,
      "ma_200": 80847
    },
    {
      "date": "2026-03-26",
      "open": 87236,
      "high": 87687,
      "low": 85186,
      "close": 85770,
      "volume": 279901,
      "ma_50": 87347,
      "ma_150": 82156,
      "ma_200": 80896
    },
    {
      "date": "2026-03-29",
      "open": 85594,
      "high": 86231,
      "low": 84285,
      "close": 84534,
      "volume": 203773,
      "ma_50": 87237,
      "ma_150": 82187,
      "ma_200": 80932
    },
    {
      "date": "2026-03-30",
      "open": 84689,
      "high": 85613,
      "low": 84080,
      "close": 85357,
      "volume": 685647,
      "ma_50": 87163,
      "ma_150": 82229,
      "ma_200": 80976
    },
    {
      "date": "2026-03-31",
      "open": 85557,
      "high": 86853,
      "low": 84985,
      "close": 86659,
      "volume": 940303,
      "ma_50": 87144,
      "ma_150": 82288,
      "ma_200": 81033
    },
    {
      "date": "2026-04-01",
      "open": 86788,
      "high": 87234,
      "low": 85272,
      "close": 85597,
      "volume": 432549,
      "ma_50": 87083,
      "ma_150": 82332,
      "ma_200": 81078
    },
    {
      "date": "2026-04-02",
      "open": 85698,
      "high": 86171,
      "low": 85048,
      "close": 85598,
      "volume": 565885,
      "ma_50": 87025,
      "ma_150": 82375,
      "ma_200": 81123
    },
    {
      "date": "2026-04-05",
      "open": 85675,
      "high": 86381,
      "low": 85244,
      "close": 85824,
      "volume": 743631,
      "ma_50": 86978,
      "ma_150": 82421,
      "ma_200": 81170
    },
    {
      "date": "2026-04-06",
      "open": 85826,
      "high": 87500,
      "low": 85680,
      "close": 87419,
      "volume": 691532,
      "ma_50": 86995,
      "ma_150": 82487,
      "ma_200": 81232
    },
    {
      "date": "2026-04-07",
      "open": 87434,
      "high": 87776,
      "low": 86666,
      "close": 86990,
      "volume": 316081,
      "ma_50": 86995,
      "ma_150": 82547,
      "ma_200": 81290
    },
    {
      "date": "2026-04-08",
      "open": 86886,
      "high": 88375,
      "low": 86249,
      "close": 88227,
      "volume": 230215,
      "ma_50": 87043,
      "ma_150": 82622,
      "ma_200": 81359
    },
    {
      "date": "2026-04-09",
      "open": 88029,
      "high": 89159,
      "low": 87985,
      "close": 88733,
      "volume": 657369,
      "ma_50": 87109,
      "ma_150": 82703,
      "ma_200": 81432
    },
    {
      "date": "2026-04-12",
      "open": 88945,
      "high": 89637,
      "low": 88405,
      "close": 88679,
      "volume": 968591,
      "ma_50": 87171,
      "ma_150": 82782,
      "ma_200": 81504
    },
    {
      "date": "2026-04-13",
      "open": 88885,
      "high": 88950,
      "low": 87428,
      "close": 87791,
      "volume": 750028,
      "ma_50": 87195,
      "ma_150": 82848,
      "ma_200": 81567
    },
    {
      "date": "2026-04-14",
      "open": 87774,
      "high": 88510,
      "low": 87144,
      "close": 87895,
      "volume": 148693,
      "ma_50": 87223,
      "ma_150": 82915,
      "ma_200": 81630
    },
    {
      "date": "2026-04-15",
      "open": 87717,
      "high": 88318,
      "low": 87436,
      "close": 87685,
      "volume": 221295,
      "ma_50": 87241,
      "ma_150": 82978,
      "ma_200": 81690
    },
    {
      "date": "2026-04-16",
      "open": 87773,
      "high": 87985,
      "low": 87033,
      "close": 87044,
      "volume": 360423,
      "ma_50": 87233,
      "ma_150": 83032,
      "ma_200": 81743
    },
    {
      "date": "2026-04-19",
      "open": 87209,
      "high": 87266,
      "low": 86237,
      "close": 86651,
      "volume": 783330,
      "ma_50": 87210,
      "ma_150": 83080,
      "ma_200": 81792
    },
    {
      "date": "2026-04-20",
      "open": 86740,
      "high": 87148,
      "low": 85266,
      "close": 85746,
      "volume": 112150,
      "ma_50": 87153,
      "ma_150": 83115,
      "ma_200": 81831
    },
    {
      "date": "2026-04-21",
      "open": 85866,
      "high": 87423,
      "low": 85541,
      "close": 87007,
      "volume": 629047,
      "ma_50": 87147,
      "ma_150": 83167,
      "ma_200": 81883
    },
    {
      "date": "2026-04-22",
      "open": 87128,
      "high": 88184,
      "low": 86856,
      "close": 87799,
      "volume": 261730,
      "ma_50": 87173,
      "ma_150": 83228,
      "ma_200": 81942
    },
    {
      "date": "2026-04-23",
      "open": 87934,
      "high": 89822,
      "low": 87725,
      "close": 89237,
      "volume": 280373,
      "ma_50": 87254,
      "ma_150": 83308,
      "ma_200": 82014
    },
    {
      "date": "2026-04-26",
      "open": 89156,
      "high": 91374,
      "low": 89049,
      "close": 90884,
      "volume": 269354,
      "ma_50": 87396,
      "ma_150": 83408,
      "ma_200": 82103
    },
    {
      "date": "2026-04-27",
      "open": 91088,
      "high": 92941,
      "low": 90702,
      "close": 92307,
      "volume": 614700,
      "ma_50": 87589,
      "ma_150": 83526,
      "ma_200": 82204
    },
    {
      "date": "2026-04-28",
      "open": 92422,
      "high": 92816,
      "low": 91891,
      "close": 92720,
      "volume": 239701,
      "ma_50": 87790,
      "ma_150": 83648,
      "ma_200": 82309
    },
    {
      "date": "2026-04-29",
      "open": 92728,
      "high": 93739,
      "low": 92195,
      "close": 93198,
      "volume": 848955,
      "ma_50": 88002,
      "ma_150": 83774,
      "ma_200": 82417
    },
    {
      "date": "2026-04-30",
      "open": 93257,
      "high": 93916,
      "low": 92761,
      "close": 93067,
      "volume": 199318,
      "ma_50": 88200,
      "ma_150": 83897,
      "ma_200": 82523
    },
    {
      "date": "2026-05-03",
      "open": 92947,
      "high": 94194,
      "low": 92495,
      "close": 93479,
      "volume": 944409,
      "ma_50": 88407,
      "ma_150": 84024,
      "ma_200": 82632
    },
    {
      "date": "2026-05-04",
      "open": 93622,
      "high": 94241,
      "low": 92916,
      "close": 93650,
      "volume": 203513,
      "ma_50": 88613,
      "ma_150": 84152,
      "ma_200": 82742
    },
    {
      "date": "2026-05-05",
      "open": 93803,
      "high": 94474,
      "low": 92605,
      "close": 92856,
      "volume": 487564,
      "ma_50": 88779,
      "ma_150": 84267,
      "ma_200": 82842
    },
    {
      "date": "2026-05-06",
      "open": 92994,
      "high": 93326,
      "low": 90957,
      "close": 91677,
      "volume": 878296,
      "ma_50": 88893,
      "ma_150": 84365,
      "ma_200": 82930
    },
    {
      "date": "2026-05-07",
      "open": 91868,
      "high": 91888,
      "low": 90046,
      "close": 90426,
      "volume": 951922,
      "ma_50": 88953,
      "ma_150": 84446,
      "ma_200": 83005
    },
    {
      "date": "2026-05-10",
      "open": 90348,
      "high": 90571,
      "low": 89331,
      "close": 89808,
      "volume": 502851,
      "ma_50": 88987,
      "ma_150": 84517,
      "ma_200": 83073
    },
    {
      "date": "2026-05-11",
      "open": 89940,
      "high": 91273,
      "low": 89688,
      "close": 91141,
      "volume": 850023,
      "ma_50": 89071,
      "ma_150": 84604,
      "ma_200": 83153
    },
    {
      "date": "2026-05-12",
      "open": 90974,
      "high": 91172,
      "low": 89955,
      "close": 90590,
      "volume": 127054,
      "ma_50": 89131,
      "ma_150": 84684,
      "ma_200": 83227
    },
    {
      "date": "2026-05-13",
      "open": 90465,
      "high": 90711,
      "low": 90126,
      "close": 90705,
      "volume": 916898,
      "ma_50": 89193,
      "ma_150": 84763,
      "ma_200": 83301
    },
    {
      "date": "2026-05-14",
      "open": 90534,
      "high": 92199,
      "low": 90494,
      "close": 91939,
      "volume": 467320,
      "ma_50": 89300,
      "ma_150": 84858,
      "ma_200": 83387
    },
    {
      "date": "2026-05-17",
      "open": 91923,
      "high": 92504,
      "low": 90399,
      "close": 90641,
      "volume": 675546,
      "ma_50": 89353,
      "ma_150": 84935,
      "ma_200": 83459
    },
    {
      "date": "2026-05-18",
      "open": 90462,
      "high": 92338,
      "low": 90418,
      "close": 92164,
      "volume": 456623,
      "ma_50": 89463,
      "ma_150": 85031,
      "ma_200": 83546
    },
    {
      "date": "2026-05-19",
      "open": 92102,
      "high": 92715,
      "low": 91975,
      "close": 92557,
      "volume": 115540,
      "ma_50": 89584,
      "ma_150": 85130,
      "ma_200": 83636
    },
    {
      "date": "2026-05-20",
      "open": 92345,
      "high": 94058,
      "low": 91633,
      "close": 93829,
      "volume": 719783,
      "ma_50": 89751,
      "ma_150": 85246,
      "ma_200": 83737
    },
    {
      "date": "2026-05-21",
      "open": 93746,
      "high": 93939,
      "low": 92973,
      "close": 93318,
      "volume": 285780,
      "ma_50": 89891,
      "ma_150": 85353,
      "ma_200": 83832
    },
    {
      "date": "2026-05-24",
      "open": 93256,
      "high": 93595,
      "low": 92418,
      "close": 93011,
      "volume": 416937,
      "ma_50": 90013,
      "ma_150": 85454,
      "ma_200": 83924
    },
    {
      "date": "2026-05-25",
      "open": 93016,
      "high": 93686,
      "low": 91202,
      "close": 91577,
      "volume": 151444,
      "ma_50": 90074,
      "ma_150": 85535,
      "ma_200": 84000
    },
    {
      "date": "2026-05-26",
      "open": 91700,
      "high": 92103,
      "low": 90072,
      "close": 90679,
      "volume": 398607,
      "ma_50": 90098,
      "ma_150": 85603,
      "ma_200": 84066
    },
    {
      "date": "2026-05-27",
      "open": 90549,
      "high": 92613,
      "low": 90252,
      "close": 92440,
      "volume": 467373,
      "ma_50": 90190,
      "ma_150": 85694,
      "ma_200": 84150
    }
  ]
}